Metadata-Version: 1.0
Name: f-matrices
Version: 0.1
Summary: matrices operations
Home-page: UNKNOWN
Author: UNKNOWN
Author-email: UNKNOWN
License: UNKNOWN
Platform: UNKNOWN
